validateFieldData.py
validateFieldData-0.4.1.dist-info/METADATA
validateFieldData-0.4.1.dist-info/WHEEL
validateFieldData-0.4.1.dist-info/top_level.txt
validateFieldData-0.4.1.dist-info/RECORD
