Metadata-Version: 2.1
Name: validateFieldData
Version: 0.4.1
Author: Samuel Reyes
License: MIT
Requires-Dist: regex
